scrfd/__init__.py
scrfd/base.py
scrfd/pub.py
scrfd/py.typed
scrfd/schemas.py
scrfd-0.3.0.dist-info/METADATA
scrfd-0.3.0.dist-info/WHEEL
scrfd-0.3.0.dist-info/licenses/LICENSE
scrfd-0.3.0.dist-info/RECORD
