Metadata-Version: 2.4
Name: scrfd
Version: 0.3.0
Summary: Efficient face detection using SCRFD
Project-URL: Repository, https://github.com/cospectrum/scrfd
Author-email: cospectrum <severinalexeyv@gmail.com>
License: Apache-2.0
License-File: LICENSE
Requires-Python: >=3.10
Requires-Dist: numpy>=2.2.0
Requires-Dist: onnxruntime>=1.20.1
Requires-Dist: pillow>=11.0.0
Requires-Dist: pydantic>=2.10.4
